visualize_sentence_diff/__init__.py
visualize_sentence_diff/visualizer.py
visualize_sentence_diff-0.0.3.dist-info/METADATA
visualize_sentence_diff-0.0.3.dist-info/WHEEL
visualize_sentence_diff-0.0.3.dist-info/licenses/LICENSE
visualize_sentence_diff-0.0.3.dist-info/RECORD
