Metadata-Version: 2.1
Name: visualize_sentence_diff
Version: 0.0.3
Summary: A python library to visualize differences between two sentences.
Project-URL: Homepage, https://github.com/ryokamoi/visualize_sentence_diff
Project-URL: Bug Tracker, https://github.com/ryokamoi/visualize_sentence_diff/issues
Author-email: Ryo Kamoi <ryokamoi.jp@gmail.com>
License: MIT License
License-File: LICENSE
Classifier: License :: OSI Approved :: MIT License
Classifier: Operating System :: OS Independent
Classifier: Programming Language :: Python :: 3
Requires-Python: >=3.7
